ImpedanceMatching/__init__.py
ImpedanceMatching/example.py
ImpedanceMatching-0.0.1.dist-info/LICENSE
ImpedanceMatching-0.0.1.dist-info/METADATA
ImpedanceMatching-0.0.1.dist-info/WHEEL
ImpedanceMatching-0.0.1.dist-info/top_level.txt
ImpedanceMatching-0.0.1.dist-info/RECORD
