Metadata-Version: 2.1
Name: ImpedanceMatching
Version: 0.0.1
Summary: impedance matching for Shock physics
Author-email: Patrick LaChapelle <patlachapelle3@gmail.com>
Project-URL: Homepage, https://github.com/WicksGroup/ImpedanceMatching
Project-URL: Issues, https://github.com/WicksGroup/ImpedanceMatching/issues
Classifier: Programming Language :: Python :: 3
Classifier: License :: OSI Approved :: MIT License
Classifier: Operating System :: OS Independent
Requires-Python: >=3.8
License-File: LICENSE
